notedb/__init__.py
notedb/dataset/__init__.py
notedb/dataset/m3u8/__init__.py
notedb/dataset/m3u8/dataset.py
notedb/dataset/m3u8/rss.py
notedb/dataset/others/__init__.py
notedb/dataset/others/dataset.py
notedb-0.0.7.dist-info/METADATA
notedb-0.0.7.dist-info/WHEEL
notedb-0.0.7.dist-info/top_level.txt
notedb-0.0.7.dist-info/RECORD
